depi/__init__.py
tests/__init__.py
tests/test_depi.py
Depi-0.0.0.dist-info/LICENSE.txt
Depi-0.0.0.dist-info/METADATA
Depi-0.0.0.dist-info/WHEEL
Depi-0.0.0.dist-info/top_level.txt
Depi-0.0.0.dist-info/RECORD
