Metadata-Version: 2.1
Name: Depi
Version: 0.0.0
Summary: Templating utilities
Home-page: https://gitlab.com/neomyte/sonotoria
Author: Emmanuel Pluot
Author-email: emmanuel.pluot@gmail.com
License: UNKNOWN
Platform: UNKNOWN
Classifier: Development Status :: 1 - Planning
Classifier: Intended Audience :: Developers
Classifier: Programming Language :: Python :: 3 :: Only
Classifier: Operating System :: Unix
Classifier: Operating System :: MacOS :: MacOS X
Classifier: Operating System :: Microsoft :: Windows
Classifier: License :: OSI Approved :: MIT License
Requires-Dist: jinja2
Requires-Dist: pyyaml
